client/__init__.py
client/client.py
client/errors.py
client/client_gui/__init__.py
client/client_gui/add_contact_gui.py
client/client_gui/client_start_gui.py
client/client_gui/main_window_gui.py
client/client_gui/sign_up_window.py
client/common/__init__.py
client/common/utils.py
client/common/variables.py
client/logs/__init__.py
client/logs/config_client_log.py
client/logs/config_server_log.py
client/unit_tests/__init__.py
client/unit_tests/test_client.py
client/unit_tests/test_server.py
client/unit_tests/test_utils.py
mess_client_redkin-0.0.1.dist-info/METADATA
mess_client_redkin-0.0.1.dist-info/WHEEL
mess_client_redkin-0.0.1.dist-info/top_level.txt
mess_client_redkin-0.0.1.dist-info/RECORD
