Metadata-Version: 2.1
Name: mess-client-redkin
Version: 0.0.1
Summary: Messenger Client
Home-page: UNKNOWN
Author: Ivan Redkin
Author-email: stazhor@bk.ru
License: UNKNOWN
Platform: UNKNOWN
Requires-Dist: PyQt5
Requires-Dist: sqlalchemy
Requires-Dist: pycryptodome
Requires-Dist: pycryptodomex
